pyrodraw/__init__.py
pyrodraw/__main__.py
pyrodraw/blocks/__init__.py
pyrodraw/blocks/cilindro.py
pyrodraw/blocks/cono.py
pyrodraw/blocks/cubo.py
pyrodraw/blocks/esfera.py
pyrodraw/blocks/flecha.py
pyrodraw/blocks/monopolo.py
pyrodraw/blocks/paralelepipedo.py
pyrodraw/blocks/spines.py
pyrodraw/blocks/tetraedro.py
pyrodraw/celda.py
pyrodraw/sistema.py
pyrodraw-2.0.0.dist-info/LICENSE
pyrodraw-2.0.0.dist-info/WHEEL
pyrodraw-2.0.0.dist-info/METADATA
pyrodraw-2.0.0.dist-info/RECORD
