Metadata-Version: 2.1
Name: pyrodraw
Version: 2.0.0
Summary: Library to draw the pyrochlore lattice and configurations of the Spin Ice model
Home-page: https://github.com/Raudcu/pyrodraw
License: MIT
Author: Lucas Pili
Requires-Python: >=3.7,<4.0
Classifier: License :: OSI Approved :: MIT License
Classifier: Programming Language :: Python :: 3
Classifier: Programming Language :: Python :: 3.7
Classifier: Programming Language :: Python :: 3.8
Classifier: Programming Language :: Python :: 3.9
Requires-Dist: matplotlib (>=3.3,<4.0)
Requires-Dist: numpy (>=1,<2)
Requires-Dist: pandas (>=1,<2)
Project-URL: Repository, https://github.com/Raudcu/pyrodraw
